patalib/__init__.py
patalib/anomaly.py
patalib/antonym.py
patalib/clinamen.py
patalib/patalib.py
patalib/synonym.py
patalib/syzygy.py
patalib-2.1.0.dist-info/licenses/LICENSE
patalib-2.1.0.dist-info/METADATA
patalib-2.1.0.dist-info/WHEEL
patalib-2.1.0.dist-info/top_level.txt
patalib-2.1.0.dist-info/RECORD
