Metadata-Version: 2.4
Name: patalib
Version: 2.1.0
Summary: Pataphysics library
Home-page: https://github.com/rpigu-i/patalib
Maintainer: rpigu-i
License: MIT
License-File: LICENSE
Requires-Dist: nltk>=3.9.1
Requires-Dist: hypothesis>=5.16.0
Dynamic: home-page
Dynamic: license
Dynamic: license-file
Dynamic: maintainer
Dynamic: requires-dist
Dynamic: summary
